seq_eval/SeqEval.py
seq_eval/__init__.py
sequence_evaluate-0.0.3.dist-info/LICENSE
sequence_evaluate-0.0.3.dist-info/METADATA
sequence_evaluate-0.0.3.dist-info/WHEEL
sequence_evaluate-0.0.3.dist-info/top_level.txt
sequence_evaluate-0.0.3.dist-info/RECORD
