Metadata-Version: 2.1
Name: sequence-evaluate
Version: 0.0.3
Summary: A python package to evaluate sequence-to-sequence models
Home-page: https://github.com/tareknaous/SeqEval
Author: Tarek Naous
Author-email: tareknaous@gmail.com
License: UNKNOWN
Platform: UNKNOWN
Classifier: Programming Language :: Python :: 3
Classifier: License :: OSI Approved :: MIT License
Classifier: Operating System :: OS Independent
Requires-Python: >=3.6
License-File: LICENSE
